{
  "$schema": "https://mintlify.com/schema.json",
  "name": "Structured",
  "logo": {
    "dark": "/logo/dark.svg",
    "light": "/logo/light.svg"
  },
  "modeToggle": {
    "default": "light",
    "isHidden": true
  },
  "favicon": "/favicon.png",
  "colors": {
    "primary": "#1d4ed8",
    "light": "#1d4ed8",
    "dark": "#1d4ed8"
  },
  "topbarLinks": [
    {
      "name": "Website",
      "url": "https://structuredlabs.com"
    },
    {
      "name": "Support",
      "url": "mailto:amrutha@structuredlabs.com"
    }
  ],
  "topbarCtaButton": {
    "name": "App",
    "url": "https://app.structuredlabs.com"
  },
  "anchors": [
    {
      "name": "Community",
      "icon": "slack",
      "url": "https://join.slack.com/t/structured-users/shared_invite/zt-265ong01f-UHP6BP3FzvOmMQDIKty_JQ"
    },
    {
      "name": "Blog",
      "icon": "newspaper",
      "url": "https://www.structuredlabs.com/blog"
    }
  ],
  "navigation": [
    {
      "group": "Get Started",
      "pages": [
        "intro",
        "quickstart"
      ]
    },
    {
      "group": "Features",
      "pages": [
        "features/comingsoon"
      ]
    },
    {
      "group": "Security Policies",
      "pages": [
        "datapolicy",
        "privacypolicy",
        "termsofservice"
      ]
    }
  ],
  "feedback": {
    "thumbsRating":true,
    "suggestEdit":true,
    "raiseIssue": true
  },
  "footerSocials": {
    "linkedin": "https://www.linkedin.com/company/structuredlabs/",
    "twitter": "https://twitter.com/StructuredLabs",
    "website": "https://www.structuredlabs.com",
    "slack": "https://structured-users.slack.com/",
    "github": "https://github.com/StructuredLabs"
  }
}